{
    "accepted_user_agreement": true,
    "admin": false,
    "admission_year": "2001",
    "avatar": "https://beta-account.chalmers.it/images/default.jpg",
    "display_name": "Fkitsmurfen",
    "full_name": "",
    "given_name": "",
    "groups": [
        "digit",
        "styrit",
        "prit",
        "nollkit",
        "sexit",
        "fanbarerit",
        "8bit",
        "drawit",
        "armit",
        "hookit",
        "fritid",
        "snit",
        "flashit",
        "valberedningen",
        "laggit",
        "fikit"
    ],
    "id": "fkitsmurf",
    "mail": "fkitsmurf@chalmers.it",
    "nickname": "Fkitsmurfen",
    "positions": {},
    "preferred_language": "sv",
    "seasonal_nickname": "Fkitsmurfen",
    "surname": "",
    "telephone_number": "",
    "uid": "fkitsmurf"
}
